pygame_event_handler/__init__.py
pygame_event_handler/event_handler.py
pygame_event_handler-0.0.2.dist-info/METADATA
pygame_event_handler-0.0.2.dist-info/WHEEL
pygame_event_handler-0.0.2.dist-info/licenses/LICENSE
pygame_event_handler-0.0.2.dist-info/RECORD
