Metadata-Version: 2.4
Name: pygame_event_handler
Version: 0.0.2
Summary: A small package that helps handling events in pygame-ce.
Project-URL: Homepage, https://github.com/awesome-open-source-projects/pygame-event-handler
Project-URL: Issues, https://github.com/awesome-open-source-projects/pygame-event-handler/issues
Author-email: yolowex <yolowex@gmail.com>
License-Expression: MIT
License-File: LICENSE
Classifier: Operating System :: OS Independent
Classifier: Programming Language :: Python :: 3
Requires-Python: >=3.9
